[
    {
        "id": "a1217bb0-602b-11e8-884c-e47a05d51ecc",
        "created_at": "Fri May 25 14:55:55 UTC 2018",
        "title": "Senior Software Engineer",
        "location": "Chicago, Illinois",
        "type": "Full Time",
        "description": "<p><strong>About Us</strong></p>\n\n<p>Braintree lets you move money from one place to another safely and securely. Every time you pay for an Uber ride, book a stay through Airbnb, or pay with PayPal when you check out online, you’re probably using our product. It sounds complex (and it is), but we make it so simple you can’t tell we’re there.</p>\n\n<p>We solve world-scale problems and provide opportunities to match. We build diverse teams that recognize our strengths and allow us to work on our weaknesses. You bring skills and a relentless focus on the customer, and we'll provide the support you need to do the best work of your life.</p>\n\n<p><strong>The Engineering Team</strong></p>\n\n<p>Our focus is teaming with smart engineers who are passionate about their craft and excited to build software for our unique solutions in the space.</p>\n\n<p>At Braintree, developers have the chance to work on various teams and stacks. Although most of our software is written in Ruby, we believe in using the best tool for the job. For example, we’ve written data platforms in Clojure, payment gateways in Java, and contextual commerce in Python. </p>\n\n<p>-Communication is key to our process, and we don't want to hinder it with walls. Many teams program in pairs, which means you always have another set of eyes to help you.</p>\n\n<p>-We practice test-driven development and believe that it helps us deliver simple solutions focused on real customer needs. We have no QA department – developers test, release and monitor their own code.</p>\n\n<p>-We keep the team in sync with daily stand-ups and have regular retrospectives to discuss things that are going well and opportunities for improvements.</p>\n\n<p>-We value unique perspectives brought by diverse backgrounds and experiences. A broad range of ideas and perspectives help us to create the best possible product.\n </p>\n\n<p><strong>Types of projects we work on</strong></p>\n\n<p>Treasury - Our platform which drives financial disbursements to merchants around the world.</p>\n\n<p>Merchant Reporting - Delivering scalable data solutions to our partners: transaction records, payment methods, currencies, &amp; features.</p>\n\n<p>Onboarding - Building out a seamless on-boarding flow for Braintree merchants across our global markets.\n </p>\n\n<p><strong>What we look for in you</strong></p>\n\n<p>-5+ years experience building software or web applications with object oriented or functional programming languages. Doesn’t matter what language, just a focus on writing clean, well designed and scalable code</p>\n\n<p>-Ability and desire to work in our collaborative environment: open team room, pair programming and fluid interactions with all products and operations teams</p>\n\n<p>-Interest in TDD and specific experiences using a test heavy approach to solve problems and create solutions</p>\n\n<p>-Focus on building solutions utilizing an agile approach: close relationships with Product Managers, communicating and digesting real time feedback, and working smart to build story cards on daily basis</p>\n\n<p><strong>Perks</strong></p>\n\n<p>-Open dev days: every two weeks we spend a day working on projects that interest us and help us expand our skills and knowledge</p>\n\n<p>-Daily catered lunches, commuter reimbursement, educational assistance, untracked PTO, employee sabbatical program</p>\n\n<p>-Generous parental &amp; family leave policies</p>\n\n<p>-Participation in the technology community: we help cover travel and attendance costs for conferences, and we offer opportunities and tools for speaking</p>\n\n<p>Check out our <a href=\"https://www.braintreepayments.com/careers\">Careers Page</a> for more company perks.\n \nWe know the <strong>confidence gap</strong> and <strong>imposter syndrome</strong> can get in the way of meeting spectacular candidates. Please don't hesitate to apply. You can also check out our FAQ!</p>\n\n<p> </p>",
        "how_to_apply": "<p><a href=\"https://grnh.se/384f79941\">https://grnh.se/384f79941</a></p>",
        "company": "Braintree Payments",
        "company_url": "https://www.braintreepayments.com/",
        "company_logo": "http://github-jobs.s3.amazonaws.com/2bc56ea8-602b-11e8-952e-c2edfdc422f5.jpg",
        "url": "http://jobs.github.com/positions/a1217bb0-602b-11e8-884c-e47a05d51ecc"
    },
    {
        "id": "1e200f24-5fcc-11e8-9968-174aac38bc5b",
        "created_at": "Fri May 25 03:32:04 UTC 2018",
        "title": "Solutions Engineer",
        "location": "North America",
        "type": "Full Time",
        "description": "<p>As a Solutions Engineer at CircleCI, you will be the customer’s trusted advisor throughout the sales process. You will provide hands on support for single tenant deployment and product guidance with CircleCI’s largest customers.</p>\n\n<p><b>About CircleCI</b></p>\n\n<p>CircleCI is the best platform for software teams looking to rapidly build quality projects, at scale. Our intelligent continuous integration and delivery tools are simple yet powerful. Our aim is to provide the wisdom of a connected development ecosystem to every team member making technology decisions.</p>\n\n<p>We run 7M+ builds a month on our platform for companies like Spotify, Kickstarter, Sony, and Coinbase. Over 25,000 organizations and 300,000 developers actively build, test, and deploy on CircleCI.  We’ve raised $59.5M in venture capital from Industry Ventures, Top Tier Capital, Scale Venture Partners, DFJ, Harrison Metal Capital, and Baseline Ventures.</p>\n\n<p><b>About Sales Solutions at CircleCI</b></p>\n\n<p>Our Solutions Engineers have a strong understanding of the developer community and are able to confidently communicate with and provide first class support to developers, DevOps leads, and architects.</p>\n\n<p>We care deeply about diversity and inclusivity. We’re hiring at all experience levels, and seek talented teammates from a wide variety of backgrounds and experiences who are equally committed to cultivating a work environment of respect and kindness. We carefully consider every applicant that takes the time to apply.</p>\n\n<p><b>RESPONSIBILITIES</b></p>\n\n<ul>\n<li>Serve as the technical lead and owner of technical deal strategy</li>\n<li>Collaborate with Account Executive to identify and uncover customer business goals, needs, and pains, and work to show how CircleCI can address them</li>\n<li>Lead the technical implementation and day-to-day management of CircleCI Trials, integrated into our customer’s technology stack - ensuring early customer success and a long-term business relationship</li>\n<li>Prove the technical feasibility of the CircleCI platform to highly technical and developer audiences</li>\n<li>Stay on top of industry news, technology products, platforms and partners to ensure you and your team provide and maintain a deep industry and ecosystem expertise</li>\n<li>Identify areas of potential improvement in our sales efforts, and then work to improve them. This could be high level strategy, daily tactical efforts, or down in the weeks of creating documentation or how to videos</li>\n<li>Custom development and launch of new sales products and customer integrations to our internal teams and customer community</li>\n<li>Partner closely with our customer success teams to ensure continuity of an amazing customer experience - for life</li>\n<li>Collaborate closely with Product and Engineering teams to help influence product roadmap based on market/customer requirements</li>\n<li>Provide technical responses to RFPs and RFIs</li>\n</ul><p><b>REQUIREMENTS</b></p>\n\n<ul>\n<li>World class presentation skills. You feel comfortable leading presentations and demos of our platform to groups, both technical and non-technical, in-person and virtually</li>\n<li>Work with customers directly to debug common errors without involving an engineer</li>\n<li>You can tie business problems to technical solutions and understand technology value propositions</li>\n<li>Demonstrated and proven capacity to quickly absorb new concepts and technologies</li>\n<li>You have spent a decent amount of time using and scripting *nix</li>\n<li>You know how to work with Git in general and ideally GitHub in particular</li>\n<li>You’ve thrown together an app or two in a high-level programming language</li>\n<li>You believe that the best way for all to succeed is to honestly discuss product and company abilities and limitations with customers. We do not oversell at CircleCI</li>\n<li>Strong ops / infrastructure knowledge, especially networking and security</li>\n</ul><p><b>ADDITIONAL SKILLS</b></p>\n\n<ul>\n<li>Experience with build, test, and deployment automation</li>\n<li>Familiarity with Clojure and/or ClojureScript</li>\n<li>Knowledge of Docker or Linux containers in general</li>\n<li>Experience with popular web app frameworks (e.g. Rails, Django) and/or mobile app development (iOS, Android)</li>\n<li>Experience using and automating a major IaaS like AWS, GCP, or Azure</li>\n<li>Familiarity deploying and debugging distributed systems</li>\n</ul><p>If you’re interested in joining the team at CircleCI, please send a resumé and cover letter describing what inspires you and why you think you are a good fit for the team. If you contribute to an open source project, write a blog, or have a presence on the web (Twitter, GitHub, LinkedIn, etc.) we would love to hear about it.</p>",
        "how_to_apply": "<p><a href=\"https://jobs.lever.co/circleci/0c519ea3-d23f-4279-8818-f2b06ce8bf51?lever-origin=applied&amp;lever-source%5B%5D=GITHUB\">https://jobs.lever.co/circleci/0c519ea3-d23f-4279-8818-f2b06ce8bf51?lever-origin=applied&amp;lever-source%5B%5D=GITHUB</a></p>",
        "company": "CircleCI",
        "company_url": "http://www.circleci.com",
        "company_logo": "http://github-jobs.s3.amazonaws.com/13ee09ca-5fcc-11e8-93e5-9465efb39d62.png",
        "url": "http://jobs.github.com/positions/1e200f24-5fcc-11e8-9968-174aac38bc5b"
    }
]
